worldcup_data/__init__.py
worldcup_data/__main__.py
worldcup_data/client/__init__.py
worldcup_data/client/matches.py
worldcup_data/constants/__init__.py
worldcup_data/constants/constants.py
worldcup_data/domain/__init__.py
worldcup_data/domain/match.py
worldcup_data_wrapper-1.0.0.dist-info/METADATA
worldcup_data_wrapper-1.0.0.dist-info/WHEEL
worldcup_data_wrapper-1.0.0.dist-info/top_level.txt
worldcup_data_wrapper-1.0.0.dist-info/RECORD
